faunadb/__init__.py
faunadb/_json.py
faunadb/client.py
faunadb/client_logger.py
faunadb/deprecated.py
faunadb/errors.py
faunadb/objects.py
faunadb/page.py
faunadb/query.py
faunadb/request_result.py
faunadb/streams/__init__.py
faunadb/streams/client.py
faunadb/streams/dispatcher.py
faunadb/streams/errors.py
faunadb/streams/events.py
faunadb/streams/subscription.py
faunadb-4.5.0.dist-info/LICENSE
faunadb-4.5.0.dist-info/METADATA
faunadb-4.5.0.dist-info/WHEEL
faunadb-4.5.0.dist-info/top_level.txt
faunadb-4.5.0.dist-info/RECORD
