Metadata-Version: 2.1
Name: faunadb
Version: 4.5.0
Summary: FaunaDB Python driver
Home-page: https://github.com/fauna/faunadb-python
Author: Fauna, Inc
Author-email: priority@fauna.com
License: MPL 2.0
Keywords: faunadb fauna
Platform: UNKNOWN
Classifier: Development Status :: 4 - Beta
Classifier: Intended Audience :: Developers
Classifier: License :: OSI Approved :: Mozilla Public License 2.0 (MPL 2.0)
Classifier: Programming Language :: Python :: 3.6
Classifier: Programming Language :: Python :: 3.7
Classifier: Programming Language :: Python :: 3.8
Classifier: Programming Language :: Python :: 3.9
Classifier: Programming Language :: Python :: 3.10
Classifier: Topic :: Database
Classifier: Topic :: Database :: Front-Ends
Classifier: Operating System :: MacOS :: MacOS X
Classifier: Operating System :: Microsoft :: Windows
Classifier: Operating System :: Unix
License-File: LICENSE
Requires-Dist: iso8601
Requires-Dist: requests
Requires-Dist: future
Requires-Dist: httpx[http2]
Provides-Extra: lint
Requires-Dist: pylint ; extra == 'lint'
Provides-Extra: test
Requires-Dist: nose2 ; extra == 'test'
Requires-Dist: nose2[coverage_plugin] ; extra == 'test'
